g2dl/__init__.py
g2dl/torch.py
g2dl-1.0.1.dist-info/LICENSE
g2dl-1.0.1.dist-info/METADATA
g2dl-1.0.1.dist-info/WHEEL
g2dl-1.0.1.dist-info/top_level.txt
g2dl-1.0.1.dist-info/zip-safe
g2dl-1.0.1.dist-info/RECORD
