Metadata-Version: 2.1
Name: g2dl
Version: 1.0.1
Summary: Gavin's Deep Learning functions
Home-page: https://github.com/chenlehua/network
Author: chenlh
Author-email: gavnlhchen@gmail.com
License: MIT
Requires-Python: >=3.8
License-File: LICENSE
Requires-Dist: torch ==2.2.0
Requires-Dist: torchvision ==0.17.0
